webcitation/api.py
webcitation/__init__.py
webcitation-0.0.2.dist-info/RECORD
webcitation-0.0.2.dist-info/metadata.json
webcitation-0.0.2.dist-info/top_level.txt
webcitation-0.0.2.dist-info/METADATA
webcitation-0.0.2.dist-info/LICENSE.txt
webcitation-0.0.2.dist-info/entry_points.txt
webcitation-0.0.2.dist-info/DESCRIPTION.rst
webcitation-0.0.2.dist-info/WHEEL
savepagenow/api.py
savepagenow/exceptions.py
savepagenow/__init__.py
