Metadata-Version: 2.0
Name: webcitation
Version: 0.0.2
Summary: A simple Python wrapper for the webcitation.org capturing service
Home-page: http://www.github.com/pastpages/webcitation/
Author: Ben Welsh
Author-email: ben.welsh@gmail.com
License: MIT
Platform: UNKNOWN
Classifier: Development Status :: 5 - Production/Stable
Classifier: Programming Language :: Python
Classifier: Programming Language :: Python :: 2
Classifier: Programming Language :: Python :: 2.7
Classifier: Programming Language :: Python :: 3
Classifier: Programming Language :: Python :: 3.5
Classifier: License :: OSI Approved :: MIT License
Requires-Dist: six
Requires-Dist: requests
Requires-Dist: click
